nutritionparser/__init__.py
nutritionparser/reader.py
nutritionparser/version.py
nutritionparser-0.1.2.dist-info/DESCRIPTION.rst
nutritionparser-0.1.2.dist-info/METADATA
nutritionparser-0.1.2.dist-info/metadata.json
nutritionparser-0.1.2.dist-info/RECORD
nutritionparser-0.1.2.dist-info/top_level.txt
nutritionparser-0.1.2.dist-info/WHEEL
