Metadata-Version: 2.0
Name: nutritionparser
Version: 0.1.2
Summary: Nutrition Parser parses USDA National Nutrient Database files.
Home-page: https://github.com/lnielsen/nutritionparser
Author: Lars Holm Nielsen
Author-email: lars@hankat.dk
License: BSD
Keywords: nutritionparser
Platform: UNKNOWN
Classifier: Intended Audience :: Developers
Classifier: License :: OSI Approved :: BSD License
Classifier: Natural Language :: English
Classifier: Programming Language :: Python :: 2
Classifier: Programming Language :: Python :: 2.6
Classifier: Programming Language :: Python :: 2.7
Classifier: Programming Language :: Python :: 3
Classifier: Programming Language :: Python :: 3.3
Classifier: Programming Language :: Python :: 3.4
